{
	"animations": [
		{
			"loop": false,
			"offsets": [
				0,
				0
			],
			"anim": "idle",
			"fps": 24,
			"name": "Idle",
			"indices": []
		},
		{
			"loop": false,
			"offsets": [
				195,
				118
			],
			"anim": "singLEFT",
			"fps": 24,
			"name": "Left",
			"indices": []
		},
		{
			"loop": false,
			"offsets": [
				-10,
				120
			],
			"anim": "singDOWN",
			"fps": 24,
			"name": "Down",
			"indices": []
		},
		{
			"loop": false,
			"offsets": [
				31,
				35
			],
			"anim": "singUP",
			"fps": 24,
			"name": "Up",
			"indices": []
		},
		{
			"loop": false,
			"offsets": [
				100,
				-21
			],
			"anim": "singRIGHT",
			"fps": 24,
			"name": "Right",
			"indices": []
		}
	],
	"no_antialiasing": true,
	"image": "characters/Sarunfunny",
	"position": [
		180,
		550
	],
	"healthicon": "icon-sarun",
	"flip_x": false,
	"healthbar_colors": [
		81,
		49,
		211
	],
	"camera_position": [
		-340,
		-270
	],
	"sing_duration": 6.1,
	"scale": 3.5
}